SECStreamPy/__init__.py
SECStreamPy/core/__init__.py
SECStreamPy/core/_rich_.py
SECStreamPy/core/_table_.py
SECStreamPy/core/_xml_.py
SECStreamPy/core/extract_text.py
SECStreamPy/core/filing.py
SECStreamPy/core/filters.py
SECStreamPy/factory/__init__.py
SECStreamPy/factory/formfactory.py
SECStreamPy/factory/patterns.py
SECStreamPy/factory/requestfactory.py
SECStreamPy/factory/scrape_financials.py
SECStreamPy/form_controller/__init__.py
SECStreamPy/form_controller/_control_10k_.py
SECStreamPy/form_controller/_control_13fhr_.py
SECStreamPy/form_controller/_control_13fnt_.py
SECStreamPy/form_controller/_control_8k_.py
SECStreamPy/form_controller/_control_d_.py
SECStreamPy/form_controller/_control_sc13d_.py
SECStreamPy/form_controller/_control_sc13g_.py
SECStreamPy/form_controller/handler.py
SECStreamPy/metadata/__init__.py
SECStreamPy/metadata/__version__.py
SECStreamPy/src/__init__.py
SECStreamPy/src/_base_request.py
SECStreamPy/src/_constants.py
SECStreamPy/src/_errors.py
SECStreamPy/src/config.py
SECStreamPy/src/data_class.py
SECStreamPy/src/generators.py
SECStreamPy/src/logger.py
SECStreamPy/src/models.py
SECStreamPy/src/utils.py
SECStreamPy/utility/__init__.py
SECStreamPy/utility/_compact_.py
secstreampy-2.2.0.dist-info/LICENSE
secstreampy-2.2.0.dist-info/METADATA
secstreampy-2.2.0.dist-info/WHEEL
secstreampy-2.2.0.dist-info/RECORD
